my_tool_package/__init__.py
my_tool_package/tools/__init__.py
my_tool_package/tools/tool_with_enabled_by_value_enum.py
my_tool_package/tools/utils.py
my_tool_package/yamls/tool_with_enabled_by_value_enum.yaml
tests/__init__.py
tests/test_my_tool_1.py
tests/test_my_tool_2.py
tests/test_tool_with_file_path_input.py
enabled_by_tool_package-0.0.2.dist-info/METADATA
enabled_by_tool_package-0.0.2.dist-info/WHEEL
enabled_by_tool_package-0.0.2.dist-info/entry_points.txt
enabled_by_tool_package-0.0.2.dist-info/top_level.txt
enabled_by_tool_package-0.0.2.dist-info/RECORD
