Metadata-Version: 2.1
Name: enabled-by-tool-package
Version: 0.0.2
Summary: This is enabled by tools package
